mongodb_queue/__init__.py
mongodb_queue/queue.py
mongodb_queue-0.1.0.dist-info/LICENSE
mongodb_queue-0.1.0.dist-info/METADATA
mongodb_queue-0.1.0.dist-info/WHEEL
mongodb_queue-0.1.0.dist-info/top_level.txt
mongodb_queue-0.1.0.dist-info/RECORD
